smolanalyst/Dockerfile
smolanalyst/cli.py
smolanalyst/constants.py
smolanalyst/filesystem.py
smolanalyst/prompt.py
smolanalyst/runner.py
smolanalyst-0.1.1.dist-info/licenses/LICENSE.md
smolanalyst-0.1.1.dist-info/METADATA
smolanalyst-0.1.1.dist-info/WHEEL
smolanalyst-0.1.1.dist-info/entry_points.txt
smolanalyst-0.1.1.dist-info/top_level.txt
smolanalyst-0.1.1.dist-info/RECORD
