Metadata-Version: 2.4
Name: smolanalyst
Version: 0.1.1
Summary: A smol AI data analyst running in the CLI
Author-email: Pierre Mallinjoud <pierre.mallinjoud@gmail.com>
Maintainer-email: Pierre Mallinjoud <pierre.mallinjoud@gmail.com>
License: MIT
Project-URL: Repository, https://github.com/smolanalyst/smolanalyst
Keywords: AI,CLI,data-analysis,agent
Classifier: Programming Language :: Python :: 3
Classifier: License :: OSI Approved :: MIT License
Classifier: Operating System :: OS Independent
Classifier: Intended Audience :: Developers
Classifier: Topic :: Scientific/Engineering :: Information Analysis
Requires-Python: >=3.12
License-File: LICENSE.md
Requires-Dist: platformdirs>=4.3.7
Requires-Dist: smolagents[litellm]>=1.14.0
Requires-Dist: typer>=0.15.3
Dynamic: license-file
